{"expireTime":9007200888920237000,"key":"bfe95e309207f11dd4f312e147d30be8","val":{"name":"IMAGE_PROCESSING","inputPaths":["/Users/ocon/main/projects/gatsby_site/gatsby-site/src/images/navBar.png"],"outputDir":"/Users/ocon/main/projects/gatsby_site/gatsby-site/public/static/721fd88714d7575ef7054720a690b8ac","args":{"isLazy":false,"operations":[{"outputPath":"c27bc/navBar.png","args":{"height":11,"width":11,"cropFocus":17,"toFormat":"png","fit":"cover"}},{"outputPath":"4b259/navBar.png","args":{"height":21,"width":21,"cropFocus":17,"toFormat":"png","fit":"cover"}},{"outputPath":"fc4a5/navBar.png","args":{"height":42,"width":42,"cropFocus":17,"toFormat":"png","fit":"cover"}},{"outputPath":"74bab/navBar.png","args":{"height":84,"width":84,"cropFocus":17,"toFormat":"png","fit":"cover"}}],"pluginOptions":{"base64Width":20,"forceBase64Format":"","useMozJpeg":false,"stripMetadata":true,"lazyImageGeneration":true,"defaultQuality":50,"failOnError":true,"plugins":[]}}}}